xcedl_image_detection/__init__.py
xcedl_image_detection/fingerprint.py
xcedl_image_detection-0.1.1.dist-info/licenses/LICENSE
xcedl_image_detection-0.1.1.dist-info/METADATA
xcedl_image_detection-0.1.1.dist-info/WHEEL
xcedl_image_detection-0.1.1.dist-info/top_level.txt
xcedl_image_detection-0.1.1.dist-info/RECORD
