Metadata-Version: 2.4
Name: Xcedl-Image-Detection
Version: 0.1.1
Summary: Advanced image fingerprinting and scam detection library
Author: Xcedl
License-Expression: MIT
Project-URL: Homepage, https://github.com/xcedl/Xcedl-Image-Detection
Project-URL: Repository, https://github.com/xcedl/Xcedl-Image-Detection.git
Project-URL: Issues, https://github.com/xcedl/Xcedl-Image-Detection/issues
Requires-Python: >=3.8
License-File: LICENSE
Requires-Dist: Pillow>=9.0.0
Requires-Dist: imagehash>=4.0
Requires-Dist: numpy>=1.20.0
Provides-Extra: dev
Requires-Dist: pytest>=6.0; extra == "dev"
Requires-Dist: black; extra == "dev"
Requires-Dist: flake8; extra == "dev"
Dynamic: license-file
